hole_c_lexer/__init__.py
hole_c_lexer/lexer.py
hole_c_lexer-1.0.1.dist-info/LICENSE
hole_c_lexer-1.0.1.dist-info/METADATA
hole_c_lexer-1.0.1.dist-info/WHEEL
hole_c_lexer-1.0.1.dist-info/entry_points.txt
hole_c_lexer-1.0.1.dist-info/top_level.txt
hole_c_lexer-1.0.1.dist-info/RECORD
